vulkn/__init__.py
vulkn/catalog.py
vulkn/config.py
vulkn/data.py
vulkn/database.py
vulkn/datatable.py
vulkn/engines.py
vulkn/profiler.py
vulkn/reader.py
vulkn/recordset.py
vulkn/scheduler.py
vulkn/session.py
vulkn/table.py
vulkn/utils.py
vulkn/apps/__init__.py
vulkn/apps/vulkn.py
vulkn/clickhouse/__init__.py
vulkn/clickhouse/client/__init__.py
vulkn/clickhouse/client/base.py
vulkn/clickhouse/client/cli.py
vulkn/clickhouse/client/http.py
vulkn/clickhouse/client/hybrid.py
vulkn/contrib/__init__.py
vulkn/contrib/sqlparse.py
vulkn/formats/__init__.py
vulkn/formats/csv.py
vulkn/funcs/__init__.py
vulkn/funcs/bitmap.py
vulkn/funcs/encode.py
vulkn/funcs/geo.py
vulkn/funcs/misc.py
vulkn/funcs/vector.py
vulkn/funcs/agg/__init__.py
vulkn/library/__init__.py
vulkn/library/core/__init__.py
vulkn/library/core/sqlext/chunk_by/__init__.py
vulkn/library/core/sqlext/vectorize_by/__init__.py
vulkn/sql/__init__.py
vulkn/sql/library.py
vulkn/sql/message.py
vulkn/sql/statement.py
vulkn/sql/utils.py
vulkn/sql/extensions/__init__.py
vulkn/sql/extensions/chunk_by.py
vulkn/sql/extensions/udf.py
vulkn/sql/extensions/vectorize_by.py
vulkn/sql/udfs/__init__.py
vulkn/sql/vector/__init__.py
vulkn/sql/vector/misc.py
vulkn/sql/vector/sql2003.py
vulkn/storages/__init__.py
vulkn/storages/posix.py
vulkn/storages/clickhouse/__init__.py
vulkn/storages/clickhouse/cli.py
vulkn/types/__init__.py
vulkn/types/array.py
vulkn/types/array_vector.py
vulkn/types/base.py
vulkn/types/boolean.py
vulkn/types/column_type.py
vulkn/types/column_vector.py
vulkn/types/date.py
vulkn/types/float.py
vulkn/types/integer.py
vulkn/types/ipaddress.py
vulkn/types/json.py
vulkn/types/keyvalue.py
vulkn/types/merge_vector.py
vulkn/types/numeric.py
vulkn/types/string.py
vulkn/types/tuple.py
vulkn/types/url.py
vulkn/types/uuid.py
vulkn/workspaces/__init__.py
vulkn/workspaces/templates/config.xml
vulkn/workspaces/templates/users.xml
vulkn-19.0.10.data/scripts/vulkn
vulkn-19.0.10.dist-info/AUTHORS
vulkn-19.0.10.dist-info/COPYING
vulkn-19.0.10.dist-info/COPYING.EXCEPTION
vulkn-19.0.10.dist-info/LICENSE
vulkn-19.0.10.dist-info/METADATA
vulkn-19.0.10.dist-info/WHEEL
vulkn-19.0.10.dist-info/top_level.txt
vulkn-19.0.10.dist-info/RECORD
