Metadata-Version: 2.1
Name: vulkn
Version: 19.0.10
Summary: The environmentally friendly petabyte scale Python eco-system built on Yandex ClickHouse
Home-page: https://github.com/VulknData/vulkn
Author: Jason Godden
Author-email: jason@vulkndata.io
License: gpl-3.0
Download-URL: https://github.com/VulknData/vulkn/archive/v19.0.10-alpha.tar.gz
Keywords: clickhouse
Platform: UNKNOWN
Classifier: Development Status :: 3 - Alpha
Classifier: Environment :: Console
Classifier: Intended Audience :: Developers
Classifier: License :: OSI Approved :: GNU General Public License v3 (GPLv3)
Classifier: Natural Language :: English
Classifier: Operating System :: POSIX :: Linux
Classifier: Programming Language :: Python :: 3
Classifier: Programming Language :: Python :: 3.7
Classifier: Topic :: Database
Classifier: Topic :: Database :: Database Engines/Servers
Classifier: Topic :: Software Development :: Libraries :: Python Modules
Requires-Python: >=3.7
Requires-Dist: ciso8601 (>=2.1.2)
Requires-Dist: numpy (>=1.18.0)
Requires-Dist: pandas (>=0.25.3)
Requires-Dist: python-dateutil (>=2.8.1)
Requires-Dist: pytz (>=2019.3)
Requires-Dist: PyYAML (>=5.2)
Requires-Dist: six (>=1.13.0)
Requires-Dist: sqlparse (>=0.3.0)
Requires-Dist: tabulate (>=0.8.6)
